embedding_encoder/__init__.py
embedding_encoder/_version.py
embedding_encoder/core.py
embedding_encoder/tests/__init__.py
embedding_encoder/tests/test_basics.py
embedding_encoder/tests/test_contrib.py
embedding_encoder/tests/test_invert.py
embedding_encoder/tests/test_sklearn.py
embedding_encoder/utils/__init__.py
embedding_encoder/utils/compose.py
embedding_encoder/utils/custom_ordinal.py
embedding_encoder-0.0.4.dist-info/LICENSE.md
embedding_encoder-0.0.4.dist-info/METADATA
embedding_encoder-0.0.4.dist-info/WHEEL
embedding_encoder-0.0.4.dist-info/top_level.txt
embedding_encoder-0.0.4.dist-info/RECORD
