Metadata-Version: 2.1
Name: embedding-encoder
Version: 0.0.4
Summary: scikit-learn compatible transformer that turns categorical features into dense numeric embeddings
Home-page: https://github.com/cpa-ferrere/EmbeddingEncoder
Author: CPA Ferrere | Data Analytics
License: MIT
Keywords: machine learning,neural network,deep learning,sklearn,scikit-learn
Platform: UNKNOWN
Classifier: Development Status :: 3 - Alpha
Classifier: Intended Audience :: Science/Research
Classifier: Intended Audience :: End Users/Desktop
Classifier: Intended Audience :: Other Audience
Classifier: Topic :: Sociology
Classifier: License :: OSI Approved :: MIT License
Classifier: Programming Language :: Python
Classifier: Programming Language :: Python :: 3.6
Classifier: Programming Language :: Python :: 3.7
Classifier: Programming Language :: Python :: 3.8
Classifier: Operating System :: OS Independent
Requires-Python: >=3.6
Requires-Dist: scikit-learn
Requires-Dist: pandas
Provides-Extra: full
Requires-Dist: tensorflow (>=2.8.0) ; extra == 'full'
Requires-Dist: seaborn ; extra == 'full'
Provides-Extra: sns
Requires-Dist: seaborn ; extra == 'sns'
Provides-Extra: tf
Requires-Dist: tensorflow (>=2.8.0) ; extra == 'tf'
